{
    "os": "Linux-5.4.0-153-generic-x86_64-with-glibc2.31",
    "python": "3.10.13",
    "heartbeatAt": "2024-05-01T07:57:10.716808",
    "startedAt": "2024-05-01T07:57:10.161738",
    "docker": null,
    "cuda": null,
    "args": [],
    "state": "running",
    "program": "/raid/home/automathon_2024/account22/Desktop/Getting Started/automathon-2024/run.py",
    "codePathLocal": "run.py",
    "codePath": "run.py",
    "git": {
        "remote": "https://github.com/OussamaZAIBI/automathon-2024.git",
        "commit": "f23bbf0db55d52f7d4540cf357f965bc655ef194"
    },
    "email": "oussama.zaibi@supcom.tn",
    "root": "/raid/home/automathon_2024/account22/Desktop/Getting Started/automathon-2024",
    "host": "dgxa100",
    "username": "account22",
    "executable": "/usr/bin/python",
    "cpu_count": 64,
    "cpu_count_logical": 128,
    "cpu_freq": {
        "current": 3229.764203124999,
        "min": 1500.0,
        "max": 2250.0
    },
    "cpu_freq_per_core": [
        {
            "current": 3230.781,
            "min": 1500.0,
            "max": 2250.0
        },
        {
            "current": 3230.59,
            "min": 1500.0,
            "max": 2250.0
        },
        {
            "current": 3230.619,
            "min": 1500.0,
            "max": 2250.0
        },
        {
            "current": 3230.595,
            "min": 1500.0,
            "max": 2250.0
        },
        {
            "current": 3217.928,
            "min": 1500.0,
            "max": 2250.0
        },
        {
            "current": 3227.506,
            "min": 1500.0,
            "max": 2250.0
        },
        {
            "current": 3089.834,
            "min": 1500.0,
            "max": 2250.0
        },
        {
            "current": 3227.324,
            "min": 1500.0,
            "max": 2250.0
        },
        {
            "current": 3227.224,
            "min": 1500.0,
            "max": 2250.0
        },
        {
            "current": 3225.754,
            "min": 1500.0,
            "max": 2250.0
        },
        {
            "current": 3227.295,
            "min": 1500.0,
            "max": 2250.0
        },
        {
            "current": 3225.296,
            "min": 1500.0,
            "max": 2250.0
        },
        {
            "current": 3227.1,
            "min": 1500.0,
            "max": 2250.0
        },
        {
            "current": 3199.601,
            "min": 1500.0,
            "max": 2250.0
        },
        {
            "current": 3226.9,
            "min": 1500.0,
            "max": 2250.0
        },
        {
            "current": 3227.015,
            "min": 1500.0,
            "max": 2250.0
        },
        {
            "current": 2963.847,
            "min": 1500.0,
            "max": 2250.0
        },
        {
            "current": 2957.002,
            "min": 1500.0,
            "max": 2250.0
        },
        {
            "current": 2965.156,
            "min": 1500.0,
            "max": 2250.0
        },
        {
            "current": 2958.238,
            "min": 1500.0,
            "max": 2250.0
        },
        {
            "current": 2908.308,
            "min": 1500.0,
            "max": 2250.0
        },
        {
            "current": 2906.103,
            "min": 1500.0,
            "max": 2250.0
        },
        {
            "current": 2909.309,
            "min": 1500.0,
            "max": 2250.0
        },
        {
            "current": 2929.035,
            "min": 1500.0,
            "max": 2250.0
        },
        {
            "current": 2897.582,
            "min": 1500.0,
            "max": 2250.0
        },
        {
            "current": 2908.539,
            "min": 1500.0,
            "max": 2250.0
        },
        {
            "current": 2897.276,
            "min": 1500.0,
            "max": 2250.0
        },
        {
            "current": 2899.046,
            "min": 1500.0,
            "max": 2250.0
        },
        {
            "current": 2896.686,
            "min": 1500.0,
            "max": 2250.0
        },
        {
            "current": 2887.087,
            "min": 1500.0,
            "max": 2250.0
        },
        {
            "current": 2889.331,
            "min": 1500.0,
            "max": 2250.0
        },
        {
            "current": 2883.362,
            "min": 1500.0,
            "max": 2250.0
        },
        {
            "current": 2827.567,
            "min": 1500.0,
            "max": 2250.0
        },
        {
            "current": 2826.325,
            "min": 1500.0,
            "max": 2250.0
        },
        {
            "current": 2838.021,
            "min": 1500.0,
            "max": 2250.0
        },
        {
            "current": 2824.484,
            "min": 1500.0,
            "max": 2250.0
        },
        {
            "current": 2830.806,
            "min": 1500.0,
            "max": 2250.0
        },
        {
            "current": 2839.712,
            "min": 1500.0,
            "max": 2250.0
        },
        {
            "current": 2834.191,
            "min": 1500.0,
            "max": 2250.0
        },
        {
            "current": 2829.146,
            "min": 1500.0,
            "max": 2250.0
        },
        {
            "current": 2876.159,
            "min": 1500.0,
            "max": 2250.0
        },
        {
            "current": 2865.957,
            "min": 1500.0,
            "max": 2250.0
        },
        {
            "current": 2854.205,
            "min": 1500.0,
            "max": 2250.0
        },
        {
            "current": 2865.574,
            "min": 1500.0,
            "max": 2250.0
        },
        {
            "current": 2841.831,
            "min": 1500.0,
            "max": 2250.0
        },
        {
            "current": 2842.127,
            "min": 1500.0,
            "max": 2250.0
        },
        {
            "current": 2831.442,
            "min": 1500.0,
            "max": 2250.0
        },
        {
            "current": 2851.809,
            "min": 1500.0,
            "max": 2250.0
        },
        {
            "current": 2842.192,
            "min": 1500.0,
            "max": 2250.0
        },
        {
            "current": 2842.482,
            "min": 1500.0,
            "max": 2250.0
        },
        {
            "current": 2853.655,
            "min": 1500.0,
            "max": 2250.0
        },
        {
            "current": 2847.576,
            "min": 1500.0,
            "max": 2250.0
        },
        {
            "current": 2819.038,
            "min": 1500.0,
            "max": 2250.0
        },
        {
            "current": 2816.739,
            "min": 1500.0,
            "max": 2250.0
        },
        {
            "current": 2808.689,
            "min": 1500.0,
            "max": 2250.0
        },
        {
            "current": 2806.124,
            "min": 1500.0,
            "max": 2250.0
        },
        {
            "current": 2817.836,
            "min": 1500.0,
            "max": 2250.0
        },
        {
            "current": 2808.204,
            "min": 1500.0,
            "max": 2250.0
        },
        {
            "current": 2811.641,
            "min": 1500.0,
            "max": 2250.0
        },
        {
            "current": 2806.55,
            "min": 1500.0,
            "max": 2250.0
        },
        {
            "current": 2809.133,
            "min": 1500.0,
            "max": 2250.0
        },
        {
            "current": 2802.199,
            "min": 1500.0,
            "max": 2250.0
        },
        {
            "current": 2802.241,
            "min": 1500.0,
            "max": 2250.0
        },
        {
            "current": 2799.132,
            "min": 1500.0,
            "max": 2250.0
        },
        {
            "current": 2792.61,
            "min": 1500.0,
            "max": 2250.0
        },
        {
            "current": 2818.926,
            "min": 1500.0,
            "max": 2250.0
        },
        {
            "current": 2947.639,
            "min": 1500.0,
            "max": 2250.0
        },
        {
            "current": 2945.107,
            "min": 1500.0,
            "max": 2250.0
        },
        {
            "current": 2950.928,
            "min": 1500.0,
            "max": 2250.0
        },
        {
            "current": 2947.827,
            "min": 1500.0,
            "max": 2250.0
        },
        {
            "current": 3010.759,
            "min": 1500.0,
            "max": 2250.0
        },
        {
            "current": 2999.437,
            "min": 1500.0,
            "max": 2250.0
        },
        {
            "current": 2939.951,
            "min": 1500.0,
            "max": 2250.0
        },
        {
            "current": 2929.207,
            "min": 1500.0,
            "max": 2250.0
        },
        {
            "current": 2949.081,
            "min": 1500.0,
            "max": 2250.0
        },
        {
            "current": 2939.088,
            "min": 1500.0,
            "max": 2250.0
        },
        {
            "current": 2929.293,
            "min": 1500.0,
            "max": 2250.0
        },
        {
            "current": 2928.396,
            "min": 1500.0,
            "max": 2250.0
        },
        {
            "current": 2930.893,
            "min": 1500.0,
            "max": 2250.0
        },
        {
            "current": 2938.654,
            "min": 1500.0,
            "max": 2250.0
        },
        {
            "current": 2924.376,
            "min": 1500.0,
            "max": 2250.0
        },
        {
            "current": 2918.176,
            "min": 1500.0,
            "max": 2250.0
        },
        {
            "current": 2925.49,
            "min": 1500.0,
            "max": 2250.0
        },
        {
            "current": 2920.094,
            "min": 1500.0,
            "max": 2250.0
        },
        {
            "current": 2878.549,
            "min": 1500.0,
            "max": 2250.0
        },
        {
            "current": 2877.149,
            "min": 1500.0,
            "max": 2250.0
        },
        {
            "current": 2879.709,
            "min": 1500.0,
            "max": 2250.0
        },
        {
            "current": 2895.877,
            "min": 1500.0,
            "max": 2250.0
        },
        {
            "current": 2839.395,
            "min": 1500.0,
            "max": 2250.0
        },
        {
            "current": 2849.189,
            "min": 1500.0,
            "max": 2250.0
        },
        {
            "current": 2840.131,
            "min": 1500.0,
            "max": 2250.0
        },
        {
            "current": 2842.335,
            "min": 1500.0,
            "max": 2250.0
        },
        {
            "current": 2850.823,
            "min": 1500.0,
            "max": 2250.0
        },
        {
            "current": 2843.357,
            "min": 1500.0,
            "max": 2250.0
        },
        {
            "current": 2845.393,
            "min": 1500.0,
            "max": 2250.0
        },
        {
            "current": 2840.906,
            "min": 1500.0,
            "max": 2250.0
        },
        {
            "current": 2811.683,
            "min": 1500.0,
            "max": 2250.0
        },
        {
            "current": 2810.38,
            "min": 1500.0,
            "max": 2250.0
        },
        {
            "current": 2820.043,
            "min": 1500.0,
            "max": 2250.0
        },
        {
            "current": 2808.512,
            "min": 1500.0,
            "max": 2250.0
        },
        {
            "current": 2814.183,
            "min": 1500.0,
            "max": 2250.0
        },
        {
            "current": 2821.383,
            "min": 1500.0,
            "max": 2250.0
        },
        {
            "current": 2816.776,
            "min": 1500.0,
            "max": 2250.0
        },
        {
            "current": 2812.31,
            "min": 1500.0,
            "max": 2250.0
        },
        {
            "current": 2823.062,
            "min": 1500.0,
            "max": 2250.0
        },
        {
            "current": 2813.911,
            "min": 1500.0,
            "max": 2250.0
        },
        {
            "current": 2803.726,
            "min": 1500.0,
            "max": 2250.0
        },
        {
            "current": 2812.535,
            "min": 1500.0,
            "max": 2250.0
        },
        {
            "current": 2820.877,
            "min": 1500.0,
            "max": 2250.0
        },
        {
            "current": 2820.159,
            "min": 1500.0,
            "max": 2250.0
        },
        {
            "current": 2810.973,
            "min": 1500.0,
            "max": 2250.0
        },
        {
            "current": 2827.549,
            "min": 1500.0,
            "max": 2250.0
        },
        {
            "current": 2805.339,
            "min": 1500.0,
            "max": 2250.0
        },
        {
            "current": 2806.183,
            "min": 1500.0,
            "max": 2250.0
        },
        {
            "current": 2815.355,
            "min": 1500.0,
            "max": 2250.0
        },
        {
            "current": 2810.047,
            "min": 1500.0,
            "max": 2250.0
        },
        {
            "current": 2799.623,
            "min": 1500.0,
            "max": 2250.0
        },
        {
            "current": 2797.477,
            "min": 1500.0,
            "max": 2250.0
        },
        {
            "current": 2790.58,
            "min": 1500.0,
            "max": 2250.0
        },
        {
            "current": 2788.139,
            "min": 1500.0,
            "max": 2250.0
        },
        {
            "current": 2778.812,
            "min": 1500.0,
            "max": 2250.0
        },
        {
            "current": 2769.957,
            "min": 1500.0,
            "max": 2250.0
        },
        {
            "current": 2772.576,
            "min": 1500.0,
            "max": 2250.0
        },
        {
            "current": 2767.525,
            "min": 1500.0,
            "max": 2250.0
        },
        {
            "current": 2786.385,
            "min": 1500.0,
            "max": 2250.0
        },
        {
            "current": 2780.561,
            "min": 1500.0,
            "max": 2250.0
        },
        {
            "current": 2780.615,
            "min": 1500.0,
            "max": 2250.0
        },
        {
            "current": 2777.939,
            "min": 1500.0,
            "max": 2250.0
        }
    ],
    "disk": {
        "/": {
            "total": 1757.8785285949707,
            "used": 380.9970397949219
        }
    },
    "memory": {
        "total": 503.7273750305176
    }
}
